django_pwyw-0.1.0.dist-info/licenses/LICENSE.md
pwyw/__init__.py
pwyw/admin.py
pwyw/apps.py
pwyw/forms.py
pwyw/models.py
pwyw/urls.py
pwyw/utils.py
django_pwyw-0.1.0.dist-info/METADATA
django_pwyw-0.1.0.dist-info/WHEEL
django_pwyw-0.1.0.dist-info/top_level.txt
django_pwyw-0.1.0.dist-info/RECORD
