Metadata-Version: 2.4
Name: django_pwyw
Version: 0.1.0
Summary: A Django app for a 'Pay What You Want' pricing model with balance tracking and QR code payments
Author-email: Christian González <office@nerdocs.at>
License-Expression: AGPL-3.0-or-later
Project-URL: Homepage, https://gitlab.com/nerdocs/django_pwyw
Project-URL: Repository, https://gitlab.com/nerdocs/django_pwyw
Project-URL: Issues, https://gitlab.com/nerdocs/django_pwyw/-/issues
Keywords: django,payment,pwyw,pay-what-you-want,qr-code,sepa
Classifier: Development Status :: 3 - Alpha
Classifier: Framework :: Django
Classifier: Framework :: Django :: 5.0
Classifier: Framework :: Django :: 6.0
Classifier: Intended Audience :: Developers
Classifier: Operating System :: OS Independent
Classifier: Programming Language :: Python
Classifier: Programming Language :: Python :: 3
Classifier: Programming Language :: Python :: 3.12
Classifier: Topic :: Software Development :: Libraries :: Python Modules
Requires-Python: >=3.12
License-File: LICENSE.md
Requires-Dist: django>=5.1
Requires-Dist: qrcode==8.2
Requires-Dist: pillow>=10.0
Provides-Extra: dev
Requires-Dist: pytest~=9.0; extra == "dev"
Requires-Dist: pytest-django~=4.11; extra == "dev"
Requires-Dist: black>=25.0; extra == "dev"
Requires-Dist: ruff>=0.14; extra == "dev"
Requires-Dist: mypy>=1.19; extra == "dev"
Requires-Dist: django-stubs>=5.2; extra == "dev"
Requires-Dist: mkdocs>=1.6; extra == "dev"
Requires-Dist: mkdocs-material>=9.7; extra == "dev"
Dynamic: license-file
